{"identifier":{"interfaceLanguage":"swift","url":"doc:\/\/TMDB\/documentation\/TMDB\/TMDB\/Configuration\/ChangeKey"},"relationshipsSections":[{"type":"conformsTo","title":"Conforms To","kind":"relationships","identifiers":["doc:\/\/TMDB\/Se","doc:\/\/TMDB\/SE","doc:\/\/TMDB\/SQ","doc:\/\/TMDB\/SH","doc:\/\/TMDB\/SY","doc:\/\/TMDB\/s8SendableP","doc:\/\/TMDB\/s16SendableMetatypeP"]}],"seeAlsoSections":[{"identifiers":["doc:\/\/TMDB\/documentation\/TMDB\/TMDB\/ConfigurationResponse","doc:\/\/TMDB\/documentation\/TMDB\/TMDB\/ImageConfiguration","doc:\/\/TMDB\/documentation\/TMDB\/TMDB\/Configuration\/ImageSize","doc:\/\/TMDB\/documentation\/TMDB\/TMDB\/Configuration\/JobDepartment","doc:\/\/TMDB\/documentation\/TMDB\/TMDB\/Configuration\/Language","doc:\/\/TMDB\/documentation\/TMDB\/TMDB\/Configuration\/Timezone"],"anchor":"Configuration-Response-Types","generated":true,"title":"Configuration Response Types"}],"hierarchy":{"paths":[["doc:\/\/TMDB\/documentation\/TMDB","doc:\/\/TMDB\/documentation\/TMDB\/TMDB","doc:\/\/TMDB\/documentation\/TMDB\/TMDB\/Configuration"]]},"kind":"symbol","topicSections":[{"anchor":"Enumeration-Cases","identifiers":["doc:\/\/TMDB\/documentation\/TMDB\/TMDB\/Configuration\/ChangeKey\/adult","doc:\/\/TMDB\/documentation\/TMDB\/TMDB\/Configuration\/ChangeKey\/airDate","doc:\/\/TMDB\/documentation\/TMDB\/TMDB\/Configuration\/ChangeKey\/alsoKnownAs","doc:\/\/TMDB\/documentation\/TMDB\/TMDB\/Configuration\/ChangeKey\/alternativeTitles","doc:\/\/TMDB\/documentation\/TMDB\/TMDB\/Configuration\/ChangeKey\/biography","doc:\/\/TMDB\/documentation\/TMDB\/TMDB\/Configuration\/ChangeKey\/birthday","doc:\/\/TMDB\/documentation\/TMDB\/TMDB\/Configuration\/ChangeKey\/budget","doc:\/\/TMDB\/documentation\/TMDB\/TMDB\/Configuration\/ChangeKey\/cast","doc:\/\/TMDB\/documentation\/TMDB\/TMDB\/Configuration\/ChangeKey\/certifications","doc:\/\/TMDB\/documentation\/TMDB\/TMDB\/Configuration\/ChangeKey\/characterNames","doc:\/\/TMDB\/documentation\/TMDB\/TMDB\/Configuration\/ChangeKey\/createdBy","doc:\/\/TMDB\/documentation\/TMDB\/TMDB\/Configuration\/ChangeKey\/crew","doc:\/\/TMDB\/documentation\/TMDB\/TMDB\/Configuration\/ChangeKey\/deathday","doc:\/\/TMDB\/documentation\/TMDB\/TMDB\/Configuration\/ChangeKey\/episode","doc:\/\/TMDB\/documentation\/TMDB\/TMDB\/Configuration\/ChangeKey\/episodeNumber","doc:\/\/TMDB\/documentation\/TMDB\/TMDB\/Configuration\/ChangeKey\/episodeRunTime","doc:\/\/TMDB\/documentation\/TMDB\/TMDB\/Configuration\/ChangeKey\/freebaseID","doc:\/\/TMDB\/documentation\/TMDB\/TMDB\/Configuration\/ChangeKey\/freebaseMid","doc:\/\/TMDB\/documentation\/TMDB\/TMDB\/Configuration\/ChangeKey\/general","doc:\/\/TMDB\/documentation\/TMDB\/TMDB\/Configuration\/ChangeKey\/genres","doc:\/\/TMDB\/documentation\/TMDB\/TMDB\/Configuration\/ChangeKey\/guestStars","doc:\/\/TMDB\/documentation\/TMDB\/TMDB\/Configuration\/ChangeKey\/homepage","doc:\/\/TMDB\/documentation\/TMDB\/TMDB\/Configuration\/ChangeKey\/images","doc:\/\/TMDB\/documentation\/TMDB\/TMDB\/Configuration\/ChangeKey\/imdbID","doc:\/\/TMDB\/documentation\/TMDB\/TMDB\/Configuration\/ChangeKey\/languages","doc:\/\/TMDB\/documentation\/TMDB\/TMDB\/Configuration\/ChangeKey\/name","doc:\/\/TMDB\/documentation\/TMDB\/TMDB\/Configuration\/ChangeKey\/network","doc:\/\/TMDB\/documentation\/TMDB\/TMDB\/Configuration\/ChangeKey\/originCountry","doc:\/\/TMDB\/documentation\/TMDB\/TMDB\/Configuration\/ChangeKey\/originalName","doc:\/\/TMDB\/documentation\/TMDB\/TMDB\/Configuration\/ChangeKey\/originalTitle","doc:\/\/TMDB\/documentation\/TMDB\/TMDB\/Configuration\/ChangeKey\/overview","doc:\/\/TMDB\/documentation\/TMDB\/TMDB\/Configuration\/ChangeKey\/parts","doc:\/\/TMDB\/documentation\/TMDB\/TMDB\/Configuration\/ChangeKey\/placeOfBirth","doc:\/\/TMDB\/documentation\/TMDB\/TMDB\/Configuration\/ChangeKey\/plotKeywords","doc:\/\/TMDB\/documentation\/TMDB\/TMDB\/Configuration\/ChangeKey\/productionCode","doc:\/\/TMDB\/documentation\/TMDB\/TMDB\/Configuration\/ChangeKey\/productionCompanies","doc:\/\/TMDB\/documentation\/TMDB\/TMDB\/Configuration\/ChangeKey\/productionCountries","doc:\/\/TMDB\/documentation\/TMDB\/TMDB\/Configuration\/ChangeKey\/releases","doc:\/\/TMDB\/documentation\/TMDB\/TMDB\/Configuration\/ChangeKey\/revenue","doc:\/\/TMDB\/documentation\/TMDB\/TMDB\/Configuration\/ChangeKey\/runtime","doc:\/\/TMDB\/documentation\/TMDB\/TMDB\/Configuration\/ChangeKey\/season","doc:\/\/TMDB\/documentation\/TMDB\/TMDB\/Configuration\/ChangeKey\/seasonNumber","doc:\/\/TMDB\/documentation\/TMDB\/TMDB\/Configuration\/ChangeKey\/seasonRegular","doc:\/\/TMDB\/documentation\/TMDB\/TMDB\/Configuration\/ChangeKey\/spokenLanguages","doc:\/\/TMDB\/documentation\/TMDB\/TMDB\/Configuration\/ChangeKey\/status","doc:\/\/TMDB\/documentation\/TMDB\/TMDB\/Configuration\/ChangeKey\/tagline","doc:\/\/TMDB\/documentation\/TMDB\/TMDB\/Configuration\/ChangeKey\/title","doc:\/\/TMDB\/documentation\/TMDB\/TMDB\/Configuration\/ChangeKey\/translations","doc:\/\/TMDB\/documentation\/TMDB\/TMDB\/Configuration\/ChangeKey\/tvdbID","doc:\/\/TMDB\/documentation\/TMDB\/TMDB\/Configuration\/ChangeKey\/tvrageID","doc:\/\/TMDB\/documentation\/TMDB\/TMDB\/Configuration\/ChangeKey\/type","doc:\/\/TMDB\/documentation\/TMDB\/TMDB\/Configuration\/ChangeKey\/video","doc:\/\/TMDB\/documentation\/TMDB\/TMDB\/Configuration\/ChangeKey\/videos"],"generated":true,"title":"Enumeration Cases"},{"anchor":"Initializers","identifiers":["doc:\/\/TMDB\/documentation\/TMDB\/TMDB\/Configuration\/ChangeKey\/init(rawValue:)"],"generated":true,"title":"Initializers"},{"anchor":"Default-Implementations","identifiers":["doc:\/\/TMDB\/documentation\/TMDB\/TMDB\/Configuration\/ChangeKey\/Equatable-Implementations","doc:\/\/TMDB\/documentation\/TMDB\/TMDB\/Configuration\/ChangeKey\/RawRepresentable-Implementations"],"generated":true,"title":"Default Implementations"}],"metadata":{"modules":[{"name":"TMDB"}],"symbolKind":"enum","roleHeading":"Enumeration","fragments":[{"text":"enum","kind":"keyword"},{"text":" ","kind":"text"},{"text":"ChangeKey","kind":"identifier"}],"extendedModule":"TMDB","navigatorTitle":[{"text":"ChangeKey","kind":"identifier"}],"role":"symbol","title":"TMDB.Configuration.ChangeKey","externalID":"s:4TMDBAAO13ConfigurationO9ChangeKeyO"},"sections":[],"variants":[{"paths":["\/documentation\/tmdb\/tmdb\/configuration\/changekey"],"traits":[{"interfaceLanguage":"swift"}]}],"primaryContentSections":[{"kind":"declarations","declarations":[{"languages":["swift"],"tokens":[{"text":"enum","kind":"keyword"},{"text":" ","kind":"text"},{"text":"ChangeKey","kind":"identifier"}],"platforms":["macOS"]}]}],"schemaVersion":{"minor":3,"patch":0,"major":0},"references":{"doc://TMDB/documentation/TMDB/TMDB/Configuration/ChangeKey/episodeRunTime":{"identifier":"doc:\/\/TMDB\/documentation\/TMDB\/TMDB\/Configuration\/ChangeKey\/episodeRunTime","abstract":[],"type":"topic","kind":"symbol","fragments":[{"kind":"keyword","text":"case"},{"kind":"text","text":" "},{"kind":"identifier","text":"episodeRunTime"}],"title":"TMDB.Configuration.ChangeKey.episodeRunTime","role":"symbol","url":"\/documentation\/tmdb\/tmdb\/configuration\/changekey\/episoderuntime"},"doc://TMDB/documentation/TMDB/TMDB/Configuration/ChangeKey/video":{"fragments":[{"kind":"keyword","text":"case"},{"kind":"text","text":" "},{"kind":"identifier","text":"video"}],"abstract":[],"kind":"symbol","identifier":"doc:\/\/TMDB\/documentation\/TMDB\/TMDB\/Configuration\/ChangeKey\/video","type":"topic","url":"\/documentation\/tmdb\/tmdb\/configuration\/changekey\/video","title":"TMDB.Configuration.ChangeKey.video","role":"symbol"},"doc://TMDB/documentation/TMDB/TMDB/Configuration/ChangeKey/seasonRegular":{"fragments":[{"kind":"keyword","text":"case"},{"kind":"text","text":" "},{"kind":"identifier","text":"seasonRegular"}],"abstract":[],"kind":"symbol","identifier":"doc:\/\/TMDB\/documentation\/TMDB\/TMDB\/Configuration\/ChangeKey\/seasonRegular","type":"topic","url":"\/documentation\/tmdb\/tmdb\/configuration\/changekey\/seasonregular","title":"TMDB.Configuration.ChangeKey.seasonRegular","role":"symbol"},"doc://TMDB/documentation/TMDB/TMDB/Configuration/ChangeKey/deathday":{"identifier":"doc:\/\/TMDB\/documentation\/TMDB\/TMDB\/Configuration\/ChangeKey\/deathday","abstract":[],"type":"topic","kind":"symbol","fragments":[{"text":"case","kind":"keyword"},{"text":" ","kind":"text"},{"text":"deathday","kind":"identifier"}],"title":"TMDB.Configuration.ChangeKey.deathday","role":"symbol","url":"\/documentation\/tmdb\/tmdb\/configuration\/changekey\/deathday"},"doc://TMDB/documentation/TMDB/TMDB/Configuration/ChangeKey/tvdbID":{"fragments":[{"text":"case","kind":"keyword"},{"text":" ","kind":"text"},{"text":"tvdbID","kind":"identifier"}],"abstract":[],"kind":"symbol","identifier":"doc:\/\/TMDB\/documentation\/TMDB\/TMDB\/Configuration\/ChangeKey\/tvdbID","type":"topic","url":"\/documentation\/tmdb\/tmdb\/configuration\/changekey\/tvdbid","title":"TMDB.Configuration.ChangeKey.tvdbID","role":"symbol"},"doc://TMDB/documentation/TMDB/TMDB/Configuration/ImageSize":{"fragments":[{"text":"enum","kind":"keyword"},{"text":" ","kind":"text"},{"text":"ImageSize","kind":"identifier"}],"navigatorTitle":[{"text":"ImageSize","kind":"identifier"}],"abstract":[],"identifier":"doc:\/\/TMDB\/documentation\/TMDB\/TMDB\/Configuration\/ImageSize","kind":"symbol","type":"topic","title":"TMDB.Configuration.ImageSize","url":"\/documentation\/tmdb\/tmdb\/configuration\/imagesize","role":"symbol"},"doc://TMDB/documentation/TMDB/TMDB/Configuration/ChangeKey/originalName":{"fragments":[{"text":"case","kind":"keyword"},{"text":" ","kind":"text"},{"text":"originalName","kind":"identifier"}],"abstract":[],"identifier":"doc:\/\/TMDB\/documentation\/TMDB\/TMDB\/Configuration\/ChangeKey\/originalName","kind":"symbol","type":"topic","title":"TMDB.Configuration.ChangeKey.originalName","url":"\/documentation\/tmdb\/tmdb\/configuration\/changekey\/originalname","role":"symbol"},"doc://TMDB/documentation/TMDB/TMDB/Configuration/ChangeKey/images":{"fragments":[{"text":"case","kind":"keyword"},{"text":" ","kind":"text"},{"text":"images","kind":"identifier"}],"abstract":[],"identifier":"doc:\/\/TMDB\/documentation\/TMDB\/TMDB\/Configuration\/ChangeKey\/images","kind":"symbol","type":"topic","title":"TMDB.Configuration.ChangeKey.images","url":"\/documentation\/tmdb\/tmdb\/configuration\/changekey\/images","role":"symbol"},"doc://TMDB/documentation/TMDB/TMDB/Configuration/ChangeKey/episode":{"fragments":[{"text":"case","kind":"keyword"},{"text":" ","kind":"text"},{"text":"episode","kind":"identifier"}],"abstract":[],"identifier":"doc:\/\/TMDB\/documentation\/TMDB\/TMDB\/Configuration\/ChangeKey\/episode","kind":"symbol","type":"topic","title":"TMDB.Configuration.ChangeKey.episode","url":"\/documentation\/tmdb\/tmdb\/configuration\/changekey\/episode","role":"symbol"},"doc://TMDB/documentation/TMDB/TMDB/Configuration/ChangeKey/alternativeTitles":{"fragments":[{"text":"case","kind":"keyword"},{"text":" ","kind":"text"},{"text":"alternativeTitles","kind":"identifier"}],"abstract":[],"identifier":"doc:\/\/TMDB\/documentation\/TMDB\/TMDB\/Configuration\/ChangeKey\/alternativeTitles","kind":"symbol","type":"topic","title":"TMDB.Configuration.ChangeKey.alternativeTitles","url":"\/documentation\/tmdb\/tmdb\/configuration\/changekey\/alternativetitles","role":"symbol"},"doc://TMDB/documentation/TMDB/TMDB/Configuration/JobDepartment":{"role":"symbol","title":"TMDB.Configuration.JobDepartment","kind":"symbol","abstract":[{"text":"Represents a job department from the ","type":"text"},{"code":"\/3\/configuration\/jobs","type":"codeVoice"},{"text":" endpoint","type":"text"}],"type":"topic","url":"\/documentation\/tmdb\/tmdb\/configuration\/jobdepartment","fragments":[{"kind":"keyword","text":"struct"},{"kind":"text","text":" "},{"kind":"identifier","text":"JobDepartment"}],"navigatorTitle":[{"kind":"identifier","text":"JobDepartment"}],"identifier":"doc:\/\/TMDB\/documentation\/TMDB\/TMDB\/Configuration\/JobDepartment"},"doc://TMDB/documentation/TMDB/TMDB/Configuration/ChangeKey/overview":{"fragments":[{"text":"case","kind":"keyword"},{"text":" ","kind":"text"},{"text":"overview","kind":"identifier"}],"abstract":[],"identifier":"doc:\/\/TMDB\/documentation\/TMDB\/TMDB\/Configuration\/ChangeKey\/overview","kind":"symbol","type":"topic","title":"TMDB.Configuration.ChangeKey.overview","url":"\/documentation\/tmdb\/tmdb\/configuration\/changekey\/overview","role":"symbol"},"doc://TMDB/documentation/TMDB/TMDB/Configuration/ChangeKey/general":{"fragments":[{"text":"case","kind":"keyword"},{"text":" ","kind":"text"},{"text":"general","kind":"identifier"}],"abstract":[],"identifier":"doc:\/\/TMDB\/documentation\/TMDB\/TMDB\/Configuration\/ChangeKey\/general","kind":"symbol","type":"topic","title":"TMDB.Configuration.ChangeKey.general","url":"\/documentation\/tmdb\/tmdb\/configuration\/changekey\/general","role":"symbol"},"doc://TMDB/documentation/TMDB/TMDB/Configuration":{"abstract":[{"text":"Namespace containing all Configuration response values","type":"text"}],"type":"topic","navigatorTitle":[{"kind":"identifier","text":"Configuration"}],"identifier":"doc:\/\/TMDB\/documentation\/TMDB\/TMDB\/Configuration","title":"TMDB.Configuration","url":"\/documentation\/tmdb\/tmdb\/configuration","kind":"symbol","fragments":[{"text":"enum","kind":"keyword"},{"text":" ","kind":"text"},{"text":"Configuration","kind":"identifier"}],"role":"symbol"},"doc://TMDB/documentation/TMDB/TMDB/Configuration/ChangeKey/homepage":{"fragments":[{"text":"case","kind":"keyword"},{"text":" ","kind":"text"},{"text":"homepage","kind":"identifier"}],"abstract":[],"identifier":"doc:\/\/TMDB\/documentation\/TMDB\/TMDB\/Configuration\/ChangeKey\/homepage","kind":"symbol","type":"topic","title":"TMDB.Configuration.ChangeKey.homepage","url":"\/documentation\/tmdb\/tmdb\/configuration\/changekey\/homepage","role":"symbol"},"doc://TMDB/documentation/TMDB/TMDB/Configuration/ChangeKey/spokenLanguages":{"fragments":[{"text":"case","kind":"keyword"},{"text":" ","kind":"text"},{"text":"spokenLanguages","kind":"identifier"}],"abstract":[],"identifier":"doc:\/\/TMDB\/documentation\/TMDB\/TMDB\/Configuration\/ChangeKey\/spokenLanguages","kind":"symbol","type":"topic","title":"TMDB.Configuration.ChangeKey.spokenLanguages","url":"\/documentation\/tmdb\/tmdb\/configuration\/changekey\/spokenlanguages","role":"symbol"},"doc://TMDB/documentation/TMDB/TMDB/Configuration/ChangeKey/genres":{"fragments":[{"text":"case","kind":"keyword"},{"text":" ","kind":"text"},{"text":"genres","kind":"identifier"}],"abstract":[],"identifier":"doc:\/\/TMDB\/documentation\/TMDB\/TMDB\/Configuration\/ChangeKey\/genres","kind":"symbol","type":"topic","title":"TMDB.Configuration.ChangeKey.genres","url":"\/documentation\/tmdb\/tmdb\/configuration\/changekey\/genres","role":"symbol"},"doc://TMDB/documentation/TMDB/TMDB/Configuration/ChangeKey/runtime":{"fragments":[{"text":"case","kind":"keyword"},{"kind":"text","text":" "},{"text":"runtime","kind":"identifier"}],"abstract":[],"identifier":"doc:\/\/TMDB\/documentation\/TMDB\/TMDB\/Configuration\/ChangeKey\/runtime","kind":"symbol","type":"topic","url":"\/documentation\/tmdb\/tmdb\/configuration\/changekey\/runtime","title":"TMDB.Configuration.ChangeKey.runtime","role":"symbol"},"doc://TMDB/documentation/TMDB/TMDB/Configuration/ChangeKey/languages":{"role":"symbol","title":"TMDB.Configuration.ChangeKey.languages","kind":"symbol","type":"topic","abstract":[],"url":"\/documentation\/tmdb\/tmdb\/configuration\/changekey\/languages","fragments":[{"text":"case","kind":"keyword"},{"text":" ","kind":"text"},{"text":"languages","kind":"identifier"}],"identifier":"doc:\/\/TMDB\/documentation\/TMDB\/TMDB\/Configuration\/ChangeKey\/languages"},"doc://TMDB/documentation/TMDB/TMDB/Configuration/ChangeKey/adult":{"role":"symbol","title":"TMDB.Configuration.ChangeKey.adult","kind":"symbol","abstract":[],"type":"topic","url":"\/documentation\/tmdb\/tmdb\/configuration\/changekey\/adult","fragments":[{"text":"case","kind":"keyword"},{"kind":"text","text":" "},{"text":"adult","kind":"identifier"}],"identifier":"doc:\/\/TMDB\/documentation\/TMDB\/TMDB\/Configuration\/ChangeKey\/adult"},"doc://TMDB/documentation/TMDB/TMDB/Configuration/ChangeKey/createdBy":{"abstract":[],"identifier":"doc:\/\/TMDB\/documentation\/TMDB\/TMDB\/Configuration\/ChangeKey\/createdBy","type":"topic","kind":"symbol","fragments":[{"kind":"keyword","text":"case"},{"kind":"text","text":" "},{"kind":"identifier","text":"createdBy"}],"title":"TMDB.Configuration.ChangeKey.createdBy","role":"symbol","url":"\/documentation\/tmdb\/tmdb\/configuration\/changekey\/createdby"},"doc://TMDB/documentation/TMDB/TMDB/Configuration/ChangeKey/tvrageID":{"fragments":[{"text":"case","kind":"keyword"},{"text":" ","kind":"text"},{"text":"tvrageID","kind":"identifier"}],"abstract":[],"identifier":"doc:\/\/TMDB\/documentation\/TMDB\/TMDB\/Configuration\/ChangeKey\/tvrageID","kind":"symbol","type":"topic","url":"\/documentation\/tmdb\/tmdb\/configuration\/changekey\/tvrageid","title":"TMDB.Configuration.ChangeKey.tvrageID","role":"symbol"},"doc://TMDB/Se":{"identifier":"doc:\/\/TMDB\/Se","type":"unresolvable","title":"Swift.Decodable"},"doc://TMDB/documentation/TMDB/TMDB/ConfigurationResponse":{"fragments":[{"text":"struct","kind":"keyword"},{"text":" ","kind":"text"},{"text":"ConfigurationResponse","kind":"identifier"}],"navigatorTitle":[{"text":"ConfigurationResponse","kind":"identifier"}],"abstract":[{"type":"text","text":"Represents the JSON response from the "},{"type":"codeVoice","code":"\/3\/configuration\/details"},{"type":"text","text":" endpoint"}],"identifier":"doc:\/\/TMDB\/documentation\/TMDB\/TMDB\/ConfigurationResponse","kind":"symbol","type":"topic","title":"TMDB.ConfigurationResponse","url":"\/documentation\/tmdb\/tmdb\/configurationresponse","role":"symbol"},"doc://TMDB/documentation/TMDB/TMDB/Configuration/ChangeKey/revenue":{"role":"symbol","title":"TMDB.Configuration.ChangeKey.revenue","kind":"symbol","type":"topic","abstract":[],"url":"\/documentation\/tmdb\/tmdb\/configuration\/changekey\/revenue","fragments":[{"text":"case","kind":"keyword"},{"text":" ","kind":"text"},{"text":"revenue","kind":"identifier"}],"identifier":"doc:\/\/TMDB\/documentation\/TMDB\/TMDB\/Configuration\/ChangeKey\/revenue"},"doc://TMDB/SH":{"type":"unresolvable","identifier":"doc:\/\/TMDB\/SH","title":"Swift.Hashable"},"doc://TMDB/documentation/TMDB/TMDB/Configuration/ChangeKey/type":{"role":"symbol","title":"TMDB.Configuration.ChangeKey.type","kind":"symbol","type":"topic","abstract":[],"url":"\/documentation\/tmdb\/tmdb\/configuration\/changekey\/type","fragments":[{"text":"case","kind":"keyword"},{"kind":"text","text":" "},{"text":"type","kind":"identifier"}],"identifier":"doc:\/\/TMDB\/documentation\/TMDB\/TMDB\/Configuration\/ChangeKey\/type"},"doc://TMDB/documentation/TMDB/TMDB/Configuration/ChangeKey/biography":{"fragments":[{"kind":"keyword","text":"case"},{"kind":"text","text":" "},{"kind":"identifier","text":"biography"}],"abstract":[],"identifier":"doc:\/\/TMDB\/documentation\/TMDB\/TMDB\/Configuration\/ChangeKey\/biography","kind":"symbol","type":"topic","url":"\/documentation\/tmdb\/tmdb\/configuration\/changekey\/biography","title":"TMDB.Configuration.ChangeKey.biography","role":"symbol"},"doc://TMDB/s16SendableMetatypeP":{"type":"unresolvable","identifier":"doc:\/\/TMDB\/s16SendableMetatypeP","title":"Swift.SendableMetatype"},"doc://TMDB/s8SendableP":{"type":"unresolvable","identifier":"doc:\/\/TMDB\/s8SendableP","title":"Swift.Sendable"},"doc://TMDB/documentation/TMDB/TMDB/Configuration/ChangeKey":{"kind":"symbol","navigatorTitle":[{"text":"ChangeKey","kind":"identifier"}],"fragments":[{"text":"enum","kind":"keyword"},{"text":" ","kind":"text"},{"text":"ChangeKey","kind":"identifier"}],"url":"\/documentation\/tmdb\/tmdb\/configuration\/changekey","role":"symbol","type":"topic","title":"TMDB.Configuration.ChangeKey","abstract":[],"identifier":"doc:\/\/TMDB\/documentation\/TMDB\/TMDB\/Configuration\/ChangeKey"},"doc://TMDB/documentation/TMDB/TMDB/Configuration/ChangeKey/birthday":{"fragments":[{"kind":"keyword","text":"case"},{"kind":"text","text":" "},{"kind":"identifier","text":"birthday"}],"abstract":[],"identifier":"doc:\/\/TMDB\/documentation\/TMDB\/TMDB\/Configuration\/ChangeKey\/birthday","kind":"symbol","type":"topic","url":"\/documentation\/tmdb\/tmdb\/configuration\/changekey\/birthday","title":"TMDB.Configuration.ChangeKey.birthday","role":"symbol"},"doc://TMDB/documentation/TMDB/TMDB/ImageConfiguration":{"fragments":[{"kind":"keyword","text":"struct"},{"kind":"text","text":" "},{"kind":"identifier","text":"ImageConfiguration"}],"navigatorTitle":[{"kind":"identifier","text":"ImageConfiguration"}],"abstract":[{"type":"text","text":"Supported image configuration details"}],"identifier":"doc:\/\/TMDB\/documentation\/TMDB\/TMDB\/ImageConfiguration","kind":"symbol","type":"topic","url":"\/documentation\/tmdb\/tmdb\/imageconfiguration","title":"TMDB.ImageConfiguration","role":"symbol"},"doc://TMDB/documentation/TMDB/TMDB/Configuration/ChangeKey/plotKeywords":{"fragments":[{"kind":"keyword","text":"case"},{"kind":"text","text":" "},{"kind":"identifier","text":"plotKeywords"}],"abstract":[],"identifier":"doc:\/\/TMDB\/documentation\/TMDB\/TMDB\/Configuration\/ChangeKey\/plotKeywords","kind":"symbol","type":"topic","url":"\/documentation\/tmdb\/tmdb\/configuration\/changekey\/plotkeywords","title":"TMDB.Configuration.ChangeKey.plotKeywords","role":"symbol"},"doc://TMDB/SQ":{"type":"unresolvable","identifier":"doc:\/\/TMDB\/SQ","title":"Swift.Equatable"},"doc://TMDB/documentation/TMDB/TMDB/Configuration/ChangeKey/productionCode":{"fragments":[{"kind":"keyword","text":"case"},{"kind":"text","text":" "},{"kind":"identifier","text":"productionCode"}],"abstract":[],"identifier":"doc:\/\/TMDB\/documentation\/TMDB\/TMDB\/Configuration\/ChangeKey\/productionCode","kind":"symbol","type":"topic","url":"\/documentation\/tmdb\/tmdb\/configuration\/changekey\/productioncode","title":"TMDB.Configuration.ChangeKey.productionCode","role":"symbol"},"doc://TMDB/documentation/TMDB/TMDB/Configuration/Language":{"identifier":"doc:\/\/TMDB\/documentation\/TMDB\/TMDB\/Configuration\/Language","abstract":[{"type":"text","text":"Represents a language from the "},{"type":"codeVoice","code":"\/3\/configuration\/languages"},{"type":"text","text":" endpoint"}],"type":"topic","kind":"symbol","fragments":[{"text":"struct","kind":"keyword"},{"text":" ","kind":"text"},{"kind":"identifier","text":"Language"}],"navigatorTitle":[{"kind":"identifier","text":"Language"}],"title":"TMDB.Configuration.Language","role":"symbol","url":"\/documentation\/tmdb\/tmdb\/configuration\/language"},"doc://TMDB/documentation/TMDB/TMDB/Configuration/ChangeKey/season":{"fragments":[{"kind":"keyword","text":"case"},{"kind":"text","text":" "},{"kind":"identifier","text":"season"}],"abstract":[],"identifier":"doc:\/\/TMDB\/documentation\/TMDB\/TMDB\/Configuration\/ChangeKey\/season","kind":"symbol","type":"topic","url":"\/documentation\/tmdb\/tmdb\/configuration\/changekey\/season","title":"TMDB.Configuration.ChangeKey.season","role":"symbol"},"doc://TMDB/documentation/TMDB/TMDB/Configuration/ChangeKey/name":{"fragments":[{"kind":"keyword","text":"case"},{"kind":"text","text":" "},{"kind":"identifier","text":"name"}],"abstract":[],"identifier":"doc:\/\/TMDB\/documentation\/TMDB\/TMDB\/Configuration\/ChangeKey\/name","kind":"symbol","type":"topic","url":"\/documentation\/tmdb\/tmdb\/configuration\/changekey\/name","title":"TMDB.Configuration.ChangeKey.name","role":"symbol"},"doc://TMDB/documentation/TMDB/TMDB/Configuration/ChangeKey/init(rawValue:)":{"fragments":[{"kind":"identifier","text":"init"},{"kind":"text","text":"?("},{"kind":"externalParam","text":"rawValue"},{"kind":"text","text":": "},{"preciseIdentifier":"s:SS","kind":"typeIdentifier","text":"String"},{"kind":"text","text":")"}],"abstract":[],"identifier":"doc:\/\/TMDB\/documentation\/TMDB\/TMDB\/Configuration\/ChangeKey\/init(rawValue:)","kind":"symbol","type":"topic","url":"\/documentation\/tmdb\/tmdb\/configuration\/changekey\/init(rawvalue:)","title":"init(rawValue:)","role":"symbol"},"doc://TMDB/documentation/TMDB/TMDB/Configuration/ChangeKey/placeOfBirth":{"fragments":[{"kind":"keyword","text":"case"},{"text":" ","kind":"text"},{"text":"placeOfBirth","kind":"identifier"}],"abstract":[],"kind":"symbol","identifier":"doc:\/\/TMDB\/documentation\/TMDB\/TMDB\/Configuration\/ChangeKey\/placeOfBirth","type":"topic","url":"\/documentation\/tmdb\/tmdb\/configuration\/changekey\/placeofbirth","title":"TMDB.Configuration.ChangeKey.placeOfBirth","role":"symbol"},"doc://TMDB/documentation/TMDB/TMDB/Configuration/ChangeKey/guestStars":{"fragments":[{"kind":"keyword","text":"case"},{"kind":"text","text":" "},{"kind":"identifier","text":"guestStars"}],"abstract":[],"identifier":"doc:\/\/TMDB\/documentation\/TMDB\/TMDB\/Configuration\/ChangeKey\/guestStars","kind":"symbol","type":"topic","url":"\/documentation\/tmdb\/tmdb\/configuration\/changekey\/gueststars","title":"TMDB.Configuration.ChangeKey.guestStars","role":"symbol"},"doc://TMDB/documentation/TMDB/TMDB/Configuration/ChangeKey/budget":{"fragments":[{"kind":"keyword","text":"case"},{"kind":"text","text":" "},{"kind":"identifier","text":"budget"}],"abstract":[],"identifier":"doc:\/\/TMDB\/documentation\/TMDB\/TMDB\/Configuration\/ChangeKey\/budget","kind":"symbol","type":"topic","url":"\/documentation\/tmdb\/tmdb\/configuration\/changekey\/budget","title":"TMDB.Configuration.ChangeKey.budget","role":"symbol"},"doc://TMDB/documentation/TMDB/TMDB/Configuration/ChangeKey/title":{"kind":"symbol","fragments":[{"text":"case","kind":"keyword"},{"text":" ","kind":"text"},{"text":"title","kind":"identifier"}],"url":"\/documentation\/tmdb\/tmdb\/configuration\/changekey\/title","role":"symbol","type":"topic","title":"TMDB.Configuration.ChangeKey.title","abstract":[],"identifier":"doc:\/\/TMDB\/documentation\/TMDB\/TMDB\/Configuration\/ChangeKey\/title"},"doc://TMDB/documentation/TMDB/TMDB/Configuration/ChangeKey/airDate":{"fragments":[{"kind":"keyword","text":"case"},{"kind":"text","text":" "},{"kind":"identifier","text":"airDate"}],"abstract":[],"identifier":"doc:\/\/TMDB\/documentation\/TMDB\/TMDB\/Configuration\/ChangeKey\/airDate","kind":"symbol","type":"topic","url":"\/documentation\/tmdb\/tmdb\/configuration\/changekey\/airdate","title":"TMDB.Configuration.ChangeKey.airDate","role":"symbol"},"doc://TMDB/documentation/TMDB/TMDB/Configuration/ChangeKey/alsoKnownAs":{"fragments":[{"kind":"keyword","text":"case"},{"kind":"text","text":" "},{"kind":"identifier","text":"alsoKnownAs"}],"abstract":[],"identifier":"doc:\/\/TMDB\/documentation\/TMDB\/TMDB\/Configuration\/ChangeKey\/alsoKnownAs","kind":"symbol","type":"topic","url":"\/documentation\/tmdb\/tmdb\/configuration\/changekey\/alsoknownas","title":"TMDB.Configuration.ChangeKey.alsoKnownAs","role":"symbol"},"doc://TMDB/documentation/TMDB/TMDB/Configuration/ChangeKey/characterNames":{"fragments":[{"kind":"keyword","text":"case"},{"kind":"text","text":" "},{"kind":"identifier","text":"characterNames"}],"abstract":[],"identifier":"doc:\/\/TMDB\/documentation\/TMDB\/TMDB\/Configuration\/ChangeKey\/characterNames","kind":"symbol","type":"topic","url":"\/documentation\/tmdb\/tmdb\/configuration\/changekey\/characternames","title":"TMDB.Configuration.ChangeKey.characterNames","role":"symbol"},"doc://TMDB/documentation/TMDB/TMDB":{"abstract":[{"text":"The top level namespace for the ","type":"text"},{"code":"swift-tmdb","type":"codeVoice"},{"text":" package","type":"text"}],"type":"topic","navigatorTitle":[{"kind":"identifier","text":"TMDB"}],"identifier":"doc:\/\/TMDB\/documentation\/TMDB\/TMDB","title":"TMDB","url":"\/documentation\/tmdb\/tmdb","kind":"symbol","fragments":[{"kind":"keyword","text":"enum"},{"text":" ","kind":"text"},{"kind":"identifier","text":"TMDB"}],"role":"symbol"},"doc://TMDB/documentation/TMDB":{"identifier":"doc:\/\/TMDB\/documentation\/TMDB","abstract":[{"text":"A Swift 6.2 wrapper around the TMDB API. Engineered for simplicity.","type":"text"}],"type":"topic","kind":"symbol","title":"TMDB","role":"collection","url":"\/documentation\/tmdb"},"doc://TMDB/documentation/TMDB/TMDB/Configuration/ChangeKey/certifications":{"role":"symbol","title":"TMDB.Configuration.ChangeKey.certifications","kind":"symbol","abstract":[],"type":"topic","url":"\/documentation\/tmdb\/tmdb\/configuration\/changekey\/certifications","fragments":[{"kind":"keyword","text":"case"},{"kind":"text","text":" "},{"kind":"identifier","text":"certifications"}],"identifier":"doc:\/\/TMDB\/documentation\/TMDB\/TMDB\/Configuration\/ChangeKey\/certifications"},"doc://TMDB/documentation/TMDB/TMDB/Configuration/ChangeKey/originCountry":{"role":"symbol","title":"TMDB.Configuration.ChangeKey.originCountry","kind":"symbol","type":"topic","abstract":[],"url":"\/documentation\/tmdb\/tmdb\/configuration\/changekey\/origincountry","fragments":[{"kind":"keyword","text":"case"},{"kind":"text","text":" "},{"kind":"identifier","text":"originCountry"}],"identifier":"doc:\/\/TMDB\/documentation\/TMDB\/TMDB\/Configuration\/ChangeKey\/originCountry"},"doc://TMDB/documentation/TMDB/TMDB/Configuration/ChangeKey/episodeNumber":{"role":"symbol","title":"TMDB.Configuration.ChangeKey.episodeNumber","kind":"symbol","type":"topic","abstract":[],"url":"\/documentation\/tmdb\/tmdb\/configuration\/changekey\/episodenumber","fragments":[{"kind":"keyword","text":"case"},{"kind":"text","text":" "},{"kind":"identifier","text":"episodeNumber"}],"identifier":"doc:\/\/TMDB\/documentation\/TMDB\/TMDB\/Configuration\/ChangeKey\/episodeNumber"},"doc://TMDB/documentation/TMDB/TMDB/Configuration/ChangeKey/videos":{"role":"symbol","title":"TMDB.Configuration.ChangeKey.videos","kind":"symbol","type":"topic","abstract":[],"url":"\/documentation\/tmdb\/tmdb\/configuration\/changekey\/videos","fragments":[{"kind":"keyword","text":"case"},{"kind":"text","text":" "},{"kind":"identifier","text":"videos"}],"identifier":"doc:\/\/TMDB\/documentation\/TMDB\/TMDB\/Configuration\/ChangeKey\/videos"},"doc://TMDB/documentation/TMDB/TMDB/Configuration/ChangeKey/cast":{"role":"symbol","title":"TMDB.Configuration.ChangeKey.cast","kind":"symbol","type":"topic","abstract":[],"url":"\/documentation\/tmdb\/tmdb\/configuration\/changekey\/cast","fragments":[{"kind":"keyword","text":"case"},{"kind":"text","text":" "},{"kind":"identifier","text":"cast"}],"identifier":"doc:\/\/TMDB\/documentation\/TMDB\/TMDB\/Configuration\/ChangeKey\/cast"},"doc://TMDB/documentation/TMDB/TMDB/Configuration/Timezone":{"role":"symbol","title":"TMDB.Configuration.Timezone","kind":"symbol","type":"topic","abstract":[{"type":"text","text":"Represents a timezone group from the "},{"type":"codeVoice","code":"\/3\/configuration\/timezones"},{"type":"text","text":" endpoint"}],"url":"\/documentation\/tmdb\/tmdb\/configuration\/timezone","fragments":[{"kind":"keyword","text":"struct"},{"kind":"text","text":" "},{"kind":"identifier","text":"Timezone"}],"navigatorTitle":[{"kind":"identifier","text":"Timezone"}],"identifier":"doc:\/\/TMDB\/documentation\/TMDB\/TMDB\/Configuration\/Timezone"},"doc://TMDB/documentation/TMDB/TMDB/Configuration/ChangeKey/crew":{"role":"symbol","title":"TMDB.Configuration.ChangeKey.crew","kind":"symbol","type":"topic","abstract":[],"url":"\/documentation\/tmdb\/tmdb\/configuration\/changekey\/crew","fragments":[{"kind":"keyword","text":"case"},{"kind":"text","text":" "},{"kind":"identifier","text":"crew"}],"identifier":"doc:\/\/TMDB\/documentation\/TMDB\/TMDB\/Configuration\/ChangeKey\/crew"},"doc://TMDB/documentation/TMDB/TMDB/Configuration/ChangeKey/freebaseMid":{"role":"symbol","title":"TMDB.Configuration.ChangeKey.freebaseMid","kind":"symbol","abstract":[],"type":"topic","url":"\/documentation\/tmdb\/tmdb\/configuration\/changekey\/freebasemid","fragments":[{"text":"case","kind":"keyword"},{"text":" ","kind":"text"},{"text":"freebaseMid","kind":"identifier"}],"identifier":"doc:\/\/TMDB\/documentation\/TMDB\/TMDB\/Configuration\/ChangeKey\/freebaseMid"},"doc://TMDB/documentation/TMDB/TMDB/Configuration/ChangeKey/RawRepresentable-Implementations":{"role":"collectionGroup","title":"RawRepresentable Implementations","kind":"article","type":"topic","abstract":[],"url":"\/documentation\/tmdb\/tmdb\/configuration\/changekey\/rawrepresentable-implementations","identifier":"doc:\/\/TMDB\/documentation\/TMDB\/TMDB\/Configuration\/ChangeKey\/RawRepresentable-Implementations"},"doc://TMDB/documentation/TMDB/TMDB/Configuration/ChangeKey/tagline":{"role":"symbol","title":"TMDB.Configuration.ChangeKey.tagline","kind":"symbol","type":"topic","abstract":[],"url":"\/documentation\/tmdb\/tmdb\/configuration\/changekey\/tagline","fragments":[{"kind":"keyword","text":"case"},{"kind":"text","text":" "},{"kind":"identifier","text":"tagline"}],"identifier":"doc:\/\/TMDB\/documentation\/TMDB\/TMDB\/Configuration\/ChangeKey\/tagline"},"doc://TMDB/documentation/TMDB/TMDB/Configuration/ChangeKey/seasonNumber":{"role":"symbol","title":"TMDB.Configuration.ChangeKey.seasonNumber","kind":"symbol","type":"topic","abstract":[],"url":"\/documentation\/tmdb\/tmdb\/configuration\/changekey\/seasonnumber","fragments":[{"kind":"keyword","text":"case"},{"kind":"text","text":" "},{"kind":"identifier","text":"seasonNumber"}],"identifier":"doc:\/\/TMDB\/documentation\/TMDB\/TMDB\/Configuration\/ChangeKey\/seasonNumber"},"doc://TMDB/documentation/TMDB/TMDB/Configuration/ChangeKey/productionCountries":{"role":"symbol","title":"TMDB.Configuration.ChangeKey.productionCountries","kind":"symbol","type":"topic","abstract":[],"url":"\/documentation\/tmdb\/tmdb\/configuration\/changekey\/productioncountries","fragments":[{"kind":"keyword","text":"case"},{"kind":"text","text":" "},{"kind":"identifier","text":"productionCountries"}],"identifier":"doc:\/\/TMDB\/documentation\/TMDB\/TMDB\/Configuration\/ChangeKey\/productionCountries"},"doc://TMDB/documentation/TMDB/TMDB/Configuration/ChangeKey/parts":{"fragments":[{"kind":"keyword","text":"case"},{"kind":"text","text":" "},{"kind":"identifier","text":"parts"}],"abstract":[],"kind":"symbol","identifier":"doc:\/\/TMDB\/documentation\/TMDB\/TMDB\/Configuration\/ChangeKey\/parts","type":"topic","title":"TMDB.Configuration.ChangeKey.parts","url":"\/documentation\/tmdb\/tmdb\/configuration\/changekey\/parts","role":"symbol"},"doc://TMDB/documentation/TMDB/TMDB/Configuration/ChangeKey/translations":{"abstract":[],"identifier":"doc:\/\/TMDB\/documentation\/TMDB\/TMDB\/Configuration\/ChangeKey\/translations","type":"topic","kind":"symbol","fragments":[{"kind":"keyword","text":"case"},{"kind":"text","text":" "},{"kind":"identifier","text":"translations"}],"title":"TMDB.Configuration.ChangeKey.translations","role":"symbol","url":"\/documentation\/tmdb\/tmdb\/configuration\/changekey\/translations"},"doc://TMDB/documentation/TMDB/TMDB/Configuration/ChangeKey/network":{"fragments":[{"kind":"keyword","text":"case"},{"kind":"text","text":" "},{"kind":"identifier","text":"network"}],"abstract":[],"kind":"symbol","identifier":"doc:\/\/TMDB\/documentation\/TMDB\/TMDB\/Configuration\/ChangeKey\/network","type":"topic","title":"TMDB.Configuration.ChangeKey.network","url":"\/documentation\/tmdb\/tmdb\/configuration\/changekey\/network","role":"symbol"},"doc://TMDB/SE":{"title":"Swift.Encodable","type":"unresolvable","identifier":"doc:\/\/TMDB\/SE"},"doc://TMDB/documentation/TMDB/TMDB/Configuration/ChangeKey/releases":{"fragments":[{"kind":"keyword","text":"case"},{"kind":"text","text":" "},{"kind":"identifier","text":"releases"}],"abstract":[],"kind":"symbol","identifier":"doc:\/\/TMDB\/documentation\/TMDB\/TMDB\/Configuration\/ChangeKey\/releases","type":"topic","title":"TMDB.Configuration.ChangeKey.releases","url":"\/documentation\/tmdb\/tmdb\/configuration\/changekey\/releases","role":"symbol"},"doc://TMDB/documentation/TMDB/TMDB/Configuration/ChangeKey/imdbID":{"fragments":[{"kind":"keyword","text":"case"},{"kind":"text","text":" "},{"kind":"identifier","text":"imdbID"}],"abstract":[],"kind":"symbol","identifier":"doc:\/\/TMDB\/documentation\/TMDB\/TMDB\/Configuration\/ChangeKey\/imdbID","type":"topic","title":"TMDB.Configuration.ChangeKey.imdbID","url":"\/documentation\/tmdb\/tmdb\/configuration\/changekey\/imdbid","role":"symbol"},"doc://TMDB/documentation/TMDB/TMDB/Configuration/ChangeKey/originalTitle":{"fragments":[{"kind":"keyword","text":"case"},{"kind":"text","text":" "},{"kind":"identifier","text":"originalTitle"}],"abstract":[],"kind":"symbol","identifier":"doc:\/\/TMDB\/documentation\/TMDB\/TMDB\/Configuration\/ChangeKey\/originalTitle","type":"topic","title":"TMDB.Configuration.ChangeKey.originalTitle","url":"\/documentation\/tmdb\/tmdb\/configuration\/changekey\/originaltitle","role":"symbol"},"doc://TMDB/documentation/TMDB/TMDB/Configuration/ChangeKey/productionCompanies":{"abstract":[],"identifier":"doc:\/\/TMDB\/documentation\/TMDB\/TMDB\/Configuration\/ChangeKey\/productionCompanies","type":"topic","kind":"symbol","fragments":[{"kind":"keyword","text":"case"},{"kind":"text","text":" "},{"kind":"identifier","text":"productionCompanies"}],"title":"TMDB.Configuration.ChangeKey.productionCompanies","role":"symbol","url":"\/documentation\/tmdb\/tmdb\/configuration\/changekey\/productioncompanies"},"doc://TMDB/documentation/TMDB/TMDB/Configuration/ChangeKey/Equatable-Implementations":{"abstract":[],"identifier":"doc:\/\/TMDB\/documentation\/TMDB\/TMDB\/Configuration\/ChangeKey\/Equatable-Implementations","type":"topic","kind":"article","title":"Equatable Implementations","role":"collectionGroup","url":"\/documentation\/tmdb\/tmdb\/configuration\/changekey\/equatable-implementations"},"doc://TMDB/documentation/TMDB/TMDB/Configuration/ChangeKey/freebaseID":{"fragments":[{"kind":"keyword","text":"case"},{"kind":"text","text":" "},{"kind":"identifier","text":"freebaseID"}],"abstract":[],"kind":"symbol","identifier":"doc:\/\/TMDB\/documentation\/TMDB\/TMDB\/Configuration\/ChangeKey\/freebaseID","type":"topic","title":"TMDB.Configuration.ChangeKey.freebaseID","url":"\/documentation\/tmdb\/tmdb\/configuration\/changekey\/freebaseid","role":"symbol"},"doc://TMDB/documentation/TMDB/TMDB/Configuration/ChangeKey/status":{"fragments":[{"kind":"keyword","text":"case"},{"kind":"text","text":" "},{"kind":"identifier","text":"status"}],"abstract":[],"kind":"symbol","identifier":"doc:\/\/TMDB\/documentation\/TMDB\/TMDB\/Configuration\/ChangeKey\/status","type":"topic","title":"TMDB.Configuration.ChangeKey.status","url":"\/documentation\/tmdb\/tmdb\/configuration\/changekey\/status","role":"symbol"},"doc://TMDB/SY":{"title":"Swift.RawRepresentable","type":"unresolvable","identifier":"doc:\/\/TMDB\/SY"}}}